stackbot/__init__.py
stackbot/main.py
stackwizard-0.0.1.dist-info/LICENSE
stackwizard-0.0.1.dist-info/METADATA
stackwizard-0.0.1.dist-info/WHEEL
stackwizard-0.0.1.dist-info/top_level.txt
stackwizard-0.0.1.dist-info/RECORD
