Metadata-Version: 2.1
Name: stackwizard
Version: 0.0.1
Summary: Provides a Stack Overflow answer when an error occurs.
Home-page: https://github.com/WillK13/AutoStack
Author: Will Kaminski
Author-email: will@kaminskis.org
Project-URL: Bug Tracker, https://github.com/WillK13/AutoStack/issues
Classifier: Programming Language :: Python :: 3
Classifier: License :: OSI Approved :: MIT License
Classifier: Operating System :: OS Independent
Requires-Python: >=3.6
License-File: LICENSE
Requires-Dist: traceback2
Requires-Dist: requests
Requires-Dist: html2text
